LICENSE
README.md
setup.py
NER/__init__.py
NER/AutoProcessor/__init__.py
NER/AutoProcessor/ParseTree/TreeAutoNER.c
NER/AutoProcessor/ParseTree/TreeAutoNER.pyx
NER/AutoProcessor/ParseTree/__init__.py
NER/AutoProcessor/Sentence/SentenceAutoNER.c
NER/AutoProcessor/Sentence/SentenceAutoNER.pxd
NER/AutoProcessor/Sentence/SentenceAutoNER.pyx
NER/AutoProcessor/Sentence/TurkishSentenceAutoNER.c
NER/AutoProcessor/Sentence/TurkishSentenceAutoNER.pyx
NER/AutoProcessor/Sentence/__init__.py
NlpToolkit_NER_Cy.egg-info/PKG-INFO
NlpToolkit_NER_Cy.egg-info/SOURCES.txt
NlpToolkit_NER_Cy.egg-info/dependency_links.txt
NlpToolkit_NER_Cy.egg-info/requires.txt
NlpToolkit_NER_Cy.egg-info/top_level.txt
nlptoolkit_ner_cy.egg-info/PKG-INFO
nlptoolkit_ner_cy.egg-info/SOURCES.txt
nlptoolkit_ner_cy.egg-info/dependency_links.txt
nlptoolkit_ner_cy.egg-info/requires.txt
nlptoolkit_ner_cy.egg-info/top_level.txt